{
  "blocks": [
    {
      "type": "simple",
      "label": "l0_0",
      "actions": [
        {
          "action": "constant-pool",
          "constant_pool": [
            "i",
            "before for/true + break",
            "in for/true + break",
            "after for/true + break"
          ]
        },
        {
          "action": "push",
          "values": [
            {
              "type": "constant",
              "value": 0
            },
            {
              "type": "float64",
              "value": 0
            }
          ]
        },
        {
          "action": "set-variable"
        },
        {
          "action": "push",
          "values": [
            {
              "type": "constant",
              "value": 1
            }
          ]
        },
        {
          "action": "trace"
        }
      ],
      "next": "l0_95"
    },
    {
      "type": "if",
      "label": "l0_95",
      "actions": [
        {
          "action": "push",
          "values": [
            {
              "type": "constant",
              "value": 2
            }
          ]
        },
        {
          "action": "trace"
        },
        {
          "action": "push",
          "values": [
            {
              "type": "constant",
              "value": 0
            },
            {
              "type": "constant",
              "value": 0
            }
          ]
        },
        {
          "action": "get-variable"
        },
        {
          "action": "push",
          "values": [
            {
              "type": "sint32",
              "value": 2
            }
          ]
        },
        {
          "action": "add2"
        },
        {
          "action": "set-variable"
        },
        {
          "action": "push",
          "values": [
            {
              "type": "constant",
              "value": 0
            }
          ]
        },
        {
          "action": "get-variable"
        },
        {
          "action": "push",
          "values": [
            {
              "type": "sint32",
              "value": 2
            }
          ]
        },
        {
          "action": "less2"
        },
        {
          "action": "not"
        },
        {
          "action": "not"
        }
      ],
      "if_true": "l0_146",
      "if_false": "l0_141"
    },
    {
      "type": "simple",
      "label": "l0_141",
      "actions": [],
      "next": "l0_151"
    },
    {
      "type": "simple",
      "label": "l0_146",
      "actions": [],
      "next": "l0_95"
    },
    {
      "type": "simple",
      "label": "l0_151",
      "actions": [
        {
          "action": "push",
          "values": [
            {
              "type": "constant",
              "value": 3
            }
          ]
        },
        {
          "action": "trace"
        }
      ],
      "next": null
    }
  ]
}
